thinknet_application_specific_exception/__init__.py
thinknet_application_specific_exception/application_specific_exception_class.py
thinknet_application_specific_exception/base_error_data_class.py
thinknet_application_specific_exception/public_functions.py
thinknet_application_specific_exception-1.0.0b4.dist-info/METADATA
thinknet_application_specific_exception-1.0.0b4.dist-info/WHEEL
thinknet_application_specific_exception-1.0.0b4.dist-info/top_level.txt
thinknet_application_specific_exception-1.0.0b4.dist-info/RECORD
