Metadata-Version: 2.2
Name: thinknet-application-specific-exception
Version: 1.0.0b4
Summary: Main error class for data-eng@thinknet
Author-email: TN-DE Team <eakamon@thinknet.co.th>
Project-URL: Homepage, https://gitlab.thinknet.co.th/data-eng/library/application-specific-exception
Classifier: Intended Audience :: Developers
Classifier: Programming Language :: Python :: 3.8
Classifier: Programming Language :: Python :: 3.9
Classifier: Programming Language :: Python :: 3.10
Classifier: Programming Language :: Python :: 3.11
Classifier: Programming Language :: Python :: 3.12
Classifier: Development Status :: 4 - Beta
Classifier: Topic :: Software Development :: Libraries
Requires-Python: >=3.8
Requires-Dist: pytz>=2024.2
Provides-Extra: dev
Requires-Dist: pytest; extra == "dev"
